[null,{"name":"Nowy","temp":"member","event-type":"6","actions":[{"info":"0","find":"474662483265847296","storage":"1","varName":"notyfikacje","name":"Find Channel"},{"channel":"5","varName":"notyfikacje","message":"${tempVars(\"member\")} właśnie dołączył do **RoyalMTA**!","storage":"0","varName2":"","name":"Send Message"}]},{"name":"Siema","temp":"msg","event-type":"2","actions":[{"message":"1","varName":"msg","info":"2","storage":"1","varName2":"text","name":"Store Message Info"},{"storage":"1","varName":"text","comparison":"6","value":"(Cześć|Elo|Siema)","iftrue":"0","iftrueVal":"","iffalse":"1","iffalseVal":"","name":"Check Variable"},{"message":"1","varName":"msg","info":"4","storage":"1","varName2":"channel","name":"Store Message Info"},{"channel":"5","varName":"channel","message":"Witaj","storage":"0","varName2":"","name":"Send Message"}]},{"name":"Prawda","temp":"msg","event-type":"2","actions":[{"message":"1","varName":"msg","info":"2","storage":"1","varName2":"text","name":"Store Message Info"},{"storage":"1","varName":"text","comparison":"6","value":"(Powiedz mi prawdę o Asperze)","iftrue":"0","iftrueVal":"","iffalse":"1","iffalseVal":"","name":"Check Variable"},{"message":"1","varName":"msg","info":"4","storage":"1","varName2":"channel","name":"Store Message Info"},{"channel":"5","varName":"channel","message":"Asper jest zajebisty, nie wiem o co wam chodzi.","storage":"0","varName2":"","name":"Send Message"}]},{"name":"klamstwo","temp":"msg","event-type":"2","actions":[{"message":"1","varName":"msg","info":"2","storage":"1","varName2":"text","name":"Store Message Info"},{"storage":"1","varName":"text","comparison":"6","value":"(Powiedz mi kłamstwo o Asperze)","iftrue":"0","iftrueVal":"","iffalse":"1","iffalseVal":"","name":"Check Variable"},{"message":"1","varName":"msg","info":"4","storage":"1","varName2":"channel","name":"Store Message Info"},{"channel":"5","varName":"channel","message":"Asper jest największym cejotem i oszustem jaki świat widział.","storage":"0","varName2":"","name":"Send Message"}]},{"name":"stworzyciel","temp":"msg","event-type":"2","actions":[{"message":"1","varName":"msg","info":"2","storage":"1","varName2":"text","name":"Store Message Info"},{"storage":"1","varName":"text","comparison":"6","value":"(Kto stworzyl bota|Kto stworzył wam bota|Kto stworzyl wam bota|Kogo bot)","iftrue":"0","iftrueVal":"","iffalse":"1","iffalseVal":"","name":"Check Variable"},{"message":"1","varName":"msg","info":"4","storage":"1","varName2":"channel","name":"Store Message Info"},{"channel":"5","varName":"channel","message":"Zostałem stworzony przez ShieldPro.","storage":"0","varName2":"","name":"Send Message"}]},{"name":"Nara","temp":"msg","event-type":"2","actions":[{"message":"1","varName":"msg","info":"2","storage":"1","varName2":"text","name":"Store Message Info"},{"storage":"1","varName":"text","comparison":"6","value":"(Nara|Pa|nara|pa)","iftrue":"0","iftrueVal":"","iffalse":"1","iffalseVal":"","name":"Check Variable"},{"message":"1","varName":"msg","info":"4","storage":"1","varName2":"channel","name":"Store Message Info"},{"channel":"5","varName":"channel","message":"Żegnaj.","storage":"0","varName2":"","name":"Send Message"}]}]